keyban_api_client/__init__.py
keyban_api_client/_version.py
keyban_api_client/client.py
keyban_api_client-0.0.7.dist-info/licenses/LICENSE
keyban_api_client-0.0.7.dist-info/METADATA
keyban_api_client-0.0.7.dist-info/WHEEL
keyban_api_client-0.0.7.dist-info/top_level.txt
keyban_api_client-0.0.7.dist-info/RECORD
