Metadata-Version: 2.4
Name: keyban-api-client
Version: 0.0.7
Summary: Python client for Keyban API
Home-page: https://github.com/keyban-io/dap
Author: Keyban
Author-email: support@keyban.io
Requires-Python: >=3.8
License-File: LICENSE
Requires-Dist: requests>=2.31.0
Requires-Dist: pydantic>=2.0.0
Requires-Dist: typing-extensions>=4.0.0
Requires-Dist: cryptography>=41.0.0
Dynamic: author
Dynamic: author-email
Dynamic: home-page
Dynamic: license-file
Dynamic: requires-python
